uv_required_version.py
uv_required_version-1.0.0.dist-info/METADATA
uv_required_version-1.0.0.dist-info/WHEEL
uv_required_version-1.0.0.dist-info/entry_points.txt
uv_required_version-1.0.0.dist-info/licenses/LICENSE
uv_required_version-1.0.0.dist-info/RECORD
