Metadata-Version: 2.4
Name: uv-required-version
Version: 1.0.0
Summary: Run uv with a specific version if required-version is set in the uv config file.
Author-email: Justin Flannery <justin.flannery@juftin.com>
License-File: LICENSE
Classifier: Development Status :: 5 - Production/Stable
Classifier: Programming Language :: Python
Classifier: Programming Language :: Python :: 3
Classifier: Programming Language :: Python :: 3.9
Classifier: Programming Language :: Python :: 3.10
Classifier: Programming Language :: Python :: 3.11
Classifier: Programming Language :: Python :: 3.12
Classifier: Programming Language :: Python :: 3.13
Requires-Python: <4,>=3.9
Requires-Dist: tomli>=1.1.0; python_version < '3.11'
Requires-Dist: uv>=0.5.14
